{
    "computeEnvironments": [
        {
            "computeEnvironmentName": "academy-v1-video-batch-ce",
            "computeEnvironmentArn": "arn:aws:batch:ap-northeast-2:809466760795:compute-environment/academy-v1-video-batch-ce",
            "ecsClusterArn": "arn:aws:ecs:ap-northeast-2:809466760795:cluster/academy-v1-video-batch-ce_Batch_003beca2-34b3-3fbd-97f6-570a2e2e34a4",
            "tags": {},
            "type": "MANAGED",
            "state": "ENABLED",
            "status": "VALID",
            "statusReason": "ComputeEnvironment Healthy",
            "computeResources": {
                "type": "EC2",
                "allocationStrategy": "BEST_FIT_PROGRESSIVE",
                "minvCpus": 0,
                "maxvCpus": 40,
                "desiredvCpus": 0,
                "instanceTypes": [
                    "c6g.xlarge"
                ],
                "subnets": [
                    "subnet-09231ed7ecf59cfa4",
                    "subnet-049e711f41fdff71b"
                ],
                "securityGroupIds": [
                    "sg-0ba6fc12209bec7de"
                ],
                "instanceRole": "arn:aws:iam::809466760795:instance-profile/academy-batch-ecs-instance-profile",
                "tags": {},
                "ec2Configuration": [
                    {
                        "imageType": "ECS_AL2023"
                    }
                ]
            },
            "serviceRole": "arn:aws:iam::809466760795:role/academy-batch-service-role",
            "containerOrchestrationType": "ECS",
            "uuid": "a63b70f6-a1bb-3e59-bbd5-aa1b6cb2acc4"
        },
        {
            "computeEnvironmentName": "academy-v1-video-ops-ce",
            "computeEnvironmentArn": "arn:aws:batch:ap-northeast-2:809466760795:compute-environment/academy-v1-video-ops-ce",
            "ecsClusterArn": "arn:aws:ecs:ap-northeast-2:809466760795:cluster/academy-v1-video-ops-ce_Batch_675e593a-6035-3719-b4d0-0fbdf521f103",
            "tags": {},
            "type": "MANAGED",
            "state": "ENABLED",
            "status": "VALID",
            "statusReason": "ComputeEnvironment Healthy",
            "computeResources": {
                "type": "EC2",
                "allocationStrategy": "BEST_FIT_PROGRESSIVE",
                "minvCpus": 0,
                "maxvCpus": 2,
                "desiredvCpus": 2,
                "instanceTypes": [
                    "m6g.medium"
                ],
                "subnets": [
                    "subnet-09231ed7ecf59cfa4",
                    "subnet-049e711f41fdff71b"
                ],
                "securityGroupIds": [
                    "sg-0ba6fc12209bec7de"
                ],
                "instanceRole": "arn:aws:iam::809466760795:instance-profile/academy-batch-ecs-instance-profile",
                "tags": {},
                "ec2Configuration": [
                    {
                        "imageType": "ECS_AL2023"
                    }
                ]
            },
            "serviceRole": "arn:aws:iam::809466760795:role/academy-batch-service-role",
            "containerOrchestrationType": "ECS",
            "uuid": "52efbbb4-d1e0-355f-a04a-04225056ffad"
        }
    ]
}
