{
    "Reservations": [
        {
            "ReservationId": "r-09aa175217ebe7e38",
            "OwnerId": "809466760795",
            "RequesterId": "154997438628",
            "Groups": [],
            "Instances": [
                {
                    "Architecture": "arm64",
                    "BlockDeviceMappings": [],
                    "ClientToken": "fleet-cd9da197-faa4-ec2f-a698-8908b7c38713-0",
                    "EbsOptimized": false,
                    "EnaSupport": true,
                    "Hypervisor": "xen",
                    "NetworkInterfaces": [],
                    "RootDeviceName": "/dev/xvda",
                    "RootDeviceType": "ebs",
                    "SecurityGroups": [],
                    "StateReason": {
                        "Code": "Client.UserInitiatedShutdown",
                        "Message": "Client.UserInitiatedShutdown: User initiated shutdown"
                    },
                    "Tags": [
                        {
                            "Key": "aws:ec2launchtemplate:version",
                            "Value": "1"
                        },
                        {
                            "Key": "aws:ec2launchtemplate:id",
                            "Value": "lt-017ef46dab75a8c00"
                        },
                        {
                            "Key": "aws:autoscaling:groupName",
                            "Value": "academy-v1-video-ops-ce-asg-823f2525-3a00-318c-85cf-2ccfc033c170"
                        },
                        {
                            "Key": "aws:ec2:fleet-id",
                            "Value": "fleet-cd9da197-faa4-ec2f-a698-8908b7c38713"
                        }
                    ],
                    "VirtualizationType": "hvm",
                    "CpuOptions": {
                        "CoreCount": 1,
                        "ThreadsPerCore": 1
                    },
                    "CapacityReservationSpecification": {
                        "CapacityReservationPreference": "open"
                    },
                    "HibernationOptions": {
                        "Configured": false
                    },
                    "MetadataOptions": {
                        "State": "pending",
                        "HttpTokens": "required",
                        "HttpPutResponseHopLimit": 2,
                        "HttpEndpoint": "enabled",
                        "HttpProtocolIpv6": "disabled",
                        "InstanceMetadataTags": "disabled"
                    },
                    "EnclaveOptions": {
                        "Enabled": false
                    },
                    "BootMode": "uefi",
                    "PlatformDetails": "Linux/UNIX",
                    "UsageOperation": "RunInstances",
                    "UsageOperationUpdateTime": "2026-03-06T06:40:08+00:00",
                    "MaintenanceOptions": {
                        "AutoRecovery": "default",
                        "RebootMigration": "default"
                    },
                    "CurrentInstanceBootMode": "uefi",
                    "NetworkPerformanceOptions": {
                        "BandwidthWeighting": "default"
                    },
                    "Operator": {
                        "Managed": false
                    },
                    "InstanceId": "i-067cad09d91e1fecb",
                    "ImageId": "ami-03d8f5845b3facccd",
                    "State": {
                        "Code": 48,
                        "Name": "terminated"
                    },
                    "PrivateDnsName": "",
                    "PublicDnsName": "",
                    "StateTransitionReason": "User initiated (2026-03-06 08:52:25 GMT)",
                    "AmiLaunchIndex": 0,
                    "ProductCodes": [],
                    "InstanceType": "m6g.medium",
                    "LaunchTime": "2026-03-06T06:40:08+00:00",
                    "Placement": {
                        "AvailabilityZoneId": "apne2-az4",
                        "GroupName": "",
                        "Tenancy": "default",
                        "AvailabilityZone": "ap-northeast-2d"
                    },
                    "Monitoring": {
                        "State": "disabled"
                    }
                }
            ]
        },
        {
            "ReservationId": "r-040c3bd26c507a94d",
            "OwnerId": "809466760795",
            "RequesterId": "154997438628",
            "Groups": [],
            "Instances": [
                {
                    "Architecture": "arm64",
                    "BlockDeviceMappings": [
                        {
                            "DeviceName": "/dev/xvda",
                            "Ebs": {
                                "AttachTime": "2026-03-06T09:09:24+00:00",
                                "DeleteOnTermination": true,
                                "Status": "attached",
                                "VolumeId": "vol-0b9e051269366423e",
                                "EbsCardIndex": 0
                            }
                        }
                    ],
                    "ClientToken": "fleet-f99d170c-6f84-66be-0418-8588d06ccfac-0",
                    "EbsOptimized": false,
                    "EnaSupport": true,
                    "Hypervisor": "xen",
                    "IamInstanceProfile": {
                        "Arn": "arn:aws:iam::809466760795:instance-profile/academy-batch-ecs-instance-profile",
                        "Id": "AIPA3Y572RZNZXIJKHZLJ"
                    },
                    "NetworkInterfaces": [
                        {
                            "Association": {
                                "IpOwnerId": "amazon",
                                "PublicDnsName": "ec2-43-203-166-55.ap-northeast-2.compute.amazonaws.com",
                                "PublicIp": "43.203.166.55"
                            },
                            "Attachment": {
                                "AttachTime": "2026-03-06T09:09:23+00:00",
                                "AttachmentId": "eni-attach-0fb6a2d9637372b0a",
                                "DeleteOnTermination": true,
                                "DeviceIndex": 0,
                                "Status": "attached",
                                "NetworkCardIndex": 0
                            },
                            "Description": "",
                            "Groups": [
                                {
                                    "GroupId": "sg-0ba6fc12209bec7de",
                                    "GroupName": "academy-v1-sg-batch"
                                }
                            ],
                            "Ipv6Addresses": [],
                            "MacAddress": "0e:87:43:4f:4b:39",
                            "NetworkInterfaceId": "eni-07e34bee99024cd60",
                            "OwnerId": "809466760795",
                            "PrivateDnsName": "ip-172-30-3-188.ap-northeast-2.compute.internal",
                            "PrivateIpAddress": "172.30.3.188",
                            "PrivateIpAddresses": [
                                {
                                    "Association": {
                                        "IpOwnerId": "amazon",
                                        "PublicDnsName": "ec2-43-203-166-55.ap-northeast-2.compute.amazonaws.com",
                                        "PublicIp": "43.203.166.55"
                                    },
                                    "Primary": true,
                                    "PrivateDnsName": "ip-172-30-3-188.ap-northeast-2.compute.internal",
                                    "PrivateIpAddress": "172.30.3.188"
                                }
                            ],
                            "SourceDestCheck": true,
                            "Status": "in-use",
                            "SubnetId": "subnet-049e711f41fdff71b",
                            "VpcId": "vpc-0831a2484f9b114c2",
                            "InterfaceType": "interface",
                            "Operator": {
                                "Managed": false
                            }
                        }
                    ],
                    "RootDeviceName": "/dev/xvda",
                    "RootDeviceType": "ebs",
                    "SecurityGroups": [
                        {
                            "GroupId": "sg-0ba6fc12209bec7de",
                            "GroupName": "academy-v1-sg-batch"
                        }
                    ],
                    "SourceDestCheck": true,
                    "Tags": [
                        {
                            "Key": "aws:autoscaling:groupName",
                            "Value": "academy-v1-video-ops-ce-asg-823f2525-3a00-318c-85cf-2ccfc033c170"
                        },
                        {
                            "Key": "aws:ec2:fleet-id",
                            "Value": "fleet-f99d170c-6f84-66be-0418-8588d06ccfac"
                        },
                        {
                            "Key": "aws:ec2launchtemplate:version",
                            "Value": "1"
                        },
                        {
                            "Key": "aws:ec2launchtemplate:id",
                            "Value": "lt-0afa0758a59af9454"
                        }
                    ],
                    "VirtualizationType": "hvm",
                    "CpuOptions": {
                        "CoreCount": 1,
                        "ThreadsPerCore": 1
                    },
                    "CapacityReservationSpecification": {
                        "CapacityReservationPreference": "open"
                    },
                    "HibernationOptions": {
                        "Configured": false
                    },
                    "MetadataOptions": {
                        "State": "applied",
                        "HttpTokens": "required",
                        "HttpPutResponseHopLimit": 2,
                        "HttpEndpoint": "enabled",
                        "HttpProtocolIpv6": "disabled",
                        "InstanceMetadataTags": "disabled"
                    },
                    "EnclaveOptions": {
                        "Enabled": false
                    },
                    "BootMode": "uefi",
                    "PlatformDetails": "Linux/UNIX",
                    "UsageOperation": "RunInstances",
                    "UsageOperationUpdateTime": "2026-03-06T09:09:23+00:00",
                    "PrivateDnsNameOptions": {
                        "HostnameType": "ip-name",
                        "EnableResourceNameDnsARecord": false,
                        "EnableResourceNameDnsAAAARecord": false
                    },
                    "MaintenanceOptions": {
                        "AutoRecovery": "default",
                        "RebootMigration": "default"
                    },
                    "CurrentInstanceBootMode": "uefi",
                    "NetworkPerformanceOptions": {
                        "BandwidthWeighting": "default"
                    },
                    "Operator": {
                        "Managed": false
                    },
                    "InstanceId": "i-0fab4214533707c93",
                    "ImageId": "ami-06589f7037b0a7e32",
                    "State": {
                        "Code": 16,
                        "Name": "running"
                    },
                    "PrivateDnsName": "ip-172-30-3-188.ap-northeast-2.compute.internal",
                    "PublicDnsName": "ec2-43-203-166-55.ap-northeast-2.compute.amazonaws.com",
                    "StateTransitionReason": "",
                    "AmiLaunchIndex": 0,
                    "ProductCodes": [],
                    "InstanceType": "m6g.medium",
                    "LaunchTime": "2026-03-06T09:09:23+00:00",
                    "Placement": {
                        "AvailabilityZoneId": "apne2-az4",
                        "GroupName": "",
                        "Tenancy": "default",
                        "AvailabilityZone": "ap-northeast-2d"
                    },
                    "Monitoring": {
                        "State": "disabled"
                    },
                    "SubnetId": "subnet-049e711f41fdff71b",
                    "VpcId": "vpc-0831a2484f9b114c2",
                    "PrivateIpAddress": "172.30.3.188",
                    "PublicIpAddress": "43.203.166.55"
                }
            ]
        },
        {
            "ReservationId": "r-023a166f7684bb25f",
            "OwnerId": "809466760795",
            "RequesterId": "154997438628",
            "Groups": [],
            "Instances": [
                {
                    "Architecture": "arm64",
                    "BlockDeviceMappings": [],
                    "ClientToken": "fleet-c7bda39d-d804-e6a5-0eba-2b2a7aa62e52-0",
                    "EbsOptimized": false,
                    "EnaSupport": true,
                    "Hypervisor": "xen",
                    "NetworkInterfaces": [],
                    "RootDeviceName": "/dev/xvda",
                    "RootDeviceType": "ebs",
                    "SecurityGroups": [],
                    "StateReason": {
                        "Code": "Client.UserInitiatedShutdown",
                        "Message": "Client.UserInitiatedShutdown: User initiated shutdown"
                    },
                    "Tags": [
                        {
                            "Key": "aws:ec2launchtemplate:version",
                            "Value": "1"
                        },
                        {
                            "Key": "aws:ec2launchtemplate:id",
                            "Value": "lt-017ef46dab75a8c00"
                        },
                        {
                            "Key": "aws:autoscaling:groupName",
                            "Value": "academy-v1-video-ops-ce-asg-823f2525-3a00-318c-85cf-2ccfc033c170"
                        },
                        {
                            "Key": "aws:ec2:fleet-id",
                            "Value": "fleet-c7bda39d-d804-e6a5-0eba-2b2a7aa62e52"
                        }
                    ],
                    "VirtualizationType": "hvm",
                    "CpuOptions": {
                        "CoreCount": 1,
                        "ThreadsPerCore": 1
                    },
                    "CapacityReservationSpecification": {
                        "CapacityReservationPreference": "open"
                    },
                    "HibernationOptions": {
                        "Configured": false
                    },
                    "MetadataOptions": {
                        "State": "pending",
                        "HttpTokens": "required",
                        "HttpPutResponseHopLimit": 2,
                        "HttpEndpoint": "enabled",
                        "HttpProtocolIpv6": "disabled",
                        "InstanceMetadataTags": "disabled"
                    },
                    "EnclaveOptions": {
                        "Enabled": false
                    },
                    "BootMode": "uefi",
                    "PlatformDetails": "Linux/UNIX",
                    "UsageOperation": "RunInstances",
                    "UsageOperationUpdateTime": "2026-03-06T06:38:03+00:00",
                    "MaintenanceOptions": {
                        "AutoRecovery": "default",
                        "RebootMigration": "default"
                    },
                    "CurrentInstanceBootMode": "uefi",
                    "NetworkPerformanceOptions": {
                        "BandwidthWeighting": "default"
                    },
                    "Operator": {
                        "Managed": false
                    },
                    "InstanceId": "i-0c5780e816193f988",
                    "ImageId": "ami-03d8f5845b3facccd",
                    "State": {
                        "Code": 48,
                        "Name": "terminated"
                    },
                    "PrivateDnsName": "",
                    "PublicDnsName": "",
                    "StateTransitionReason": "User initiated (2026-03-06 08:52:25 GMT)",
                    "AmiLaunchIndex": 0,
                    "ProductCodes": [],
                    "InstanceType": "m6g.medium",
                    "LaunchTime": "2026-03-06T06:38:03+00:00",
                    "Placement": {
                        "AvailabilityZoneId": "apne2-az2",
                        "GroupName": "",
                        "Tenancy": "default",
                        "AvailabilityZone": "ap-northeast-2b"
                    },
                    "Monitoring": {
                        "State": "disabled"
                    }
                }
            ]
        },
        {
            "ReservationId": "r-0ef8d68e8911a811d",
            "OwnerId": "809466760795",
            "Groups": [],
            "Instances": [
                {
                    "Architecture": "arm64",
                    "BlockDeviceMappings": [
                        {
                            "DeviceName": "/dev/xvda",
                            "Ebs": {
                                "AttachTime": "2026-03-06T06:37:43+00:00",
                                "DeleteOnTermination": true,
                                "Status": "attached",
                                "VolumeId": "vol-0415dacaf3cf4ac86",
                                "EbsCardIndex": 0
                            }
                        }
                    ],
                    "ClientToken": "fcd284fb-e4ba-44a8-bf31-48332fc61cfe",
                    "EbsOptimized": false,
                    "EnaSupport": true,
                    "Hypervisor": "xen",
                    "IamInstanceProfile": {
                        "Arn": "arn:aws:iam::809466760795:instance-profile/academy-ec2-role",
                        "Id": "AIPA3Y572RZNQDBTRV633"
                    },
                    "NetworkInterfaces": [
                        {
                            "Association": {
                                "IpOwnerId": "amazon",
                                "PublicDnsName": "ec2-43-203-99-186.ap-northeast-2.compute.amazonaws.com",
                                "PublicIp": "43.203.99.186"
                            },
                            "Attachment": {
                                "AttachTime": "2026-03-06T06:37:42+00:00",
                                "AttachmentId": "eni-attach-0c562eb66a3f76bed",
                                "DeleteOnTermination": true,
                                "DeviceIndex": 0,
                                "Status": "attached",
                                "NetworkCardIndex": 0
                            },
                            "Description": "",
                            "Groups": [
                                {
                                    "GroupId": "sg-088fa3315c12754d0",
                                    "GroupName": "academy-v1-sg-app"
                                }
                            ],
                            "Ipv6Addresses": [],
                            "MacAddress": "06:2b:0f:94:f5:cf",
                            "NetworkInterfaceId": "eni-0b7324e904e44a198",
                            "OwnerId": "809466760795",
                            "PrivateDnsName": "ip-172-30-1-99.ap-northeast-2.compute.internal",
                            "PrivateIpAddress": "172.30.1.99",
                            "PrivateIpAddresses": [
                                {
                                    "Association": {
                                        "IpOwnerId": "amazon",
                                        "PublicDnsName": "ec2-43-203-99-186.ap-northeast-2.compute.amazonaws.com",
                                        "PublicIp": "43.203.99.186"
                                    },
                                    "Primary": true,
                                    "PrivateDnsName": "ip-172-30-1-99.ap-northeast-2.compute.internal",
                                    "PrivateIpAddress": "172.30.1.99"
                                }
                            ],
                            "SourceDestCheck": true,
                            "Status": "in-use",
                            "SubnetId": "subnet-09231ed7ecf59cfa4",
                            "VpcId": "vpc-0831a2484f9b114c2",
                            "InterfaceType": "interface",
                            "Operator": {
                                "Managed": false
                            }
                        }
                    ],
                    "RootDeviceName": "/dev/xvda",
                    "RootDeviceType": "ebs",
                    "SecurityGroups": [
                        {
                            "GroupId": "sg-088fa3315c12754d0",
                            "GroupName": "academy-v1-sg-app"
                        }
                    ],
                    "SourceDestCheck": true,
                    "Tags": [
                        {
                            "Key": "Name",
                            "Value": "academy-build-arm64"
                        }
                    ],
                    "VirtualizationType": "hvm",
                    "CpuOptions": {
                        "CoreCount": 2,
                        "ThreadsPerCore": 1
                    },
                    "CapacityReservationSpecification": {
                        "CapacityReservationPreference": "open"
                    },
                    "HibernationOptions": {
                        "Configured": false
                    },
                    "MetadataOptions": {
                        "State": "applied",
                        "HttpTokens": "required",
                        "HttpPutResponseHopLimit": 2,
                        "HttpEndpoint": "enabled",
                        "HttpProtocolIpv6": "disabled",
                        "InstanceMetadataTags": "disabled"
                    },
                    "EnclaveOptions": {
                        "Enabled": false
                    },
                    "BootMode": "uefi",
                    "PlatformDetails": "Linux/UNIX",
                    "UsageOperation": "RunInstances",
                    "UsageOperationUpdateTime": "2026-03-06T06:37:42+00:00",
                    "PrivateDnsNameOptions": {
                        "HostnameType": "ip-name",
                        "EnableResourceNameDnsARecord": false,
                        "EnableResourceNameDnsAAAARecord": false
                    },
                    "MaintenanceOptions": {
                        "AutoRecovery": "default",
                        "RebootMigration": "default"
                    },
                    "CurrentInstanceBootMode": "uefi",
                    "NetworkPerformanceOptions": {
                        "BandwidthWeighting": "default"
                    },
                    "Operator": {
                        "Managed": false
                    },
                    "InstanceId": "i-0c11e7127e7ea03f8",
                    "ImageId": "ami-0885e191a9bcf28b0",
                    "State": {
                        "Code": 16,
                        "Name": "running"
                    },
                    "PrivateDnsName": "ip-172-30-1-99.ap-northeast-2.compute.internal",
                    "PublicDnsName": "ec2-43-203-99-186.ap-northeast-2.compute.amazonaws.com",
                    "StateTransitionReason": "",
                    "AmiLaunchIndex": 0,
                    "ProductCodes": [],
                    "InstanceType": "t4g.medium",
                    "LaunchTime": "2026-03-06T06:37:42+00:00",
                    "Placement": {
                        "AvailabilityZoneId": "apne2-az2",
                        "GroupName": "",
                        "Tenancy": "default",
                        "AvailabilityZone": "ap-northeast-2b"
                    },
                    "Monitoring": {
                        "State": "disabled"
                    },
                    "SubnetId": "subnet-09231ed7ecf59cfa4",
                    "VpcId": "vpc-0831a2484f9b114c2",
                    "PrivateIpAddress": "172.30.1.99",
                    "PublicIpAddress": "43.203.99.186"
                }
            ]
        },
        {
            "ReservationId": "r-0bcda1a42482fbceb",
            "OwnerId": "809466760795",
            "RequesterId": "154997438628",
            "Groups": [],
            "Instances": [
                {
                    "Architecture": "arm64",
                    "BlockDeviceMappings": [
                        {
                            "DeviceName": "/dev/xvda",
                            "Ebs": {
                                "AttachTime": "2026-03-06T09:13:31+00:00",
                                "DeleteOnTermination": true,
                                "Status": "attached",
                                "VolumeId": "vol-023ff43bcb966b462",
                                "EbsCardIndex": 0
                            }
                        }
                    ],
                    "ClientToken": "fleet-e5352bb7-5a0e-ee0d-24b2-012a38706889-0",
                    "EbsOptimized": false,
                    "EnaSupport": true,
                    "Hypervisor": "xen",
                    "IamInstanceProfile": {
                        "Arn": "arn:aws:iam::809466760795:instance-profile/academy-batch-ecs-instance-profile",
                        "Id": "AIPA3Y572RZNZXIJKHZLJ"
                    },
                    "NetworkInterfaces": [
                        {
                            "Association": {
                                "IpOwnerId": "amazon",
                                "PublicDnsName": "ec2-13-125-203-237.ap-northeast-2.compute.amazonaws.com",
                                "PublicIp": "13.125.203.237"
                            },
                            "Attachment": {
                                "AttachTime": "2026-03-06T09:13:31+00:00",
                                "AttachmentId": "eni-attach-021202bdba6fbeaa9",
                                "DeleteOnTermination": true,
                                "DeviceIndex": 0,
                                "Status": "attached",
                                "NetworkCardIndex": 0
                            },
                            "Description": "",
                            "Groups": [
                                {
                                    "GroupId": "sg-0ba6fc12209bec7de",
                                    "GroupName": "academy-v1-sg-batch"
                                }
                            ],
                            "Ipv6Addresses": [],
                            "MacAddress": "06:10:c8:de:83:d7",
                            "NetworkInterfaceId": "eni-06e727499818a7e15",
                            "OwnerId": "809466760795",
                            "PrivateDnsName": "ip-172-30-1-247.ap-northeast-2.compute.internal",
                            "PrivateIpAddress": "172.30.1.247",
                            "PrivateIpAddresses": [
                                {
                                    "Association": {
                                        "IpOwnerId": "amazon",
                                        "PublicDnsName": "ec2-13-125-203-237.ap-northeast-2.compute.amazonaws.com",
                                        "PublicIp": "13.125.203.237"
                                    },
                                    "Primary": true,
                                    "PrivateDnsName": "ip-172-30-1-247.ap-northeast-2.compute.internal",
                                    "PrivateIpAddress": "172.30.1.247"
                                }
                            ],
                            "SourceDestCheck": true,
                            "Status": "in-use",
                            "SubnetId": "subnet-09231ed7ecf59cfa4",
                            "VpcId": "vpc-0831a2484f9b114c2",
                            "InterfaceType": "interface",
                            "Operator": {
                                "Managed": false
                            }
                        }
                    ],
                    "RootDeviceName": "/dev/xvda",
                    "RootDeviceType": "ebs",
                    "SecurityGroups": [
                        {
                            "GroupId": "sg-0ba6fc12209bec7de",
                            "GroupName": "academy-v1-sg-batch"
                        }
                    ],
                    "SourceDestCheck": true,
                    "Tags": [
                        {
                            "Key": "aws:ec2launchtemplate:version",
                            "Value": "1"
                        },
                        {
                            "Key": "aws:ec2launchtemplate:id",
                            "Value": "lt-0afa0758a59af9454"
                        },
                        {
                            "Key": "aws:ec2:fleet-id",
                            "Value": "fleet-e5352bb7-5a0e-ee0d-24b2-012a38706889"
                        },
                        {
                            "Key": "aws:autoscaling:groupName",
                            "Value": "academy-v1-video-ops-ce-asg-823f2525-3a00-318c-85cf-2ccfc033c170"
                        }
                    ],
                    "VirtualizationType": "hvm",
                    "CpuOptions": {
                        "CoreCount": 1,
                        "ThreadsPerCore": 1
                    },
                    "CapacityReservationSpecification": {
                        "CapacityReservationPreference": "open"
                    },
                    "HibernationOptions": {
                        "Configured": false
                    },
                    "MetadataOptions": {
                        "State": "applied",
                        "HttpTokens": "required",
                        "HttpPutResponseHopLimit": 2,
                        "HttpEndpoint": "enabled",
                        "HttpProtocolIpv6": "disabled",
                        "InstanceMetadataTags": "disabled"
                    },
                    "EnclaveOptions": {
                        "Enabled": false
                    },
                    "BootMode": "uefi",
                    "PlatformDetails": "Linux/UNIX",
                    "UsageOperation": "RunInstances",
                    "UsageOperationUpdateTime": "2026-03-06T09:13:31+00:00",
                    "PrivateDnsNameOptions": {
                        "HostnameType": "ip-name",
                        "EnableResourceNameDnsARecord": false,
                        "EnableResourceNameDnsAAAARecord": false
                    },
                    "MaintenanceOptions": {
                        "AutoRecovery": "default",
                        "RebootMigration": "default"
                    },
                    "CurrentInstanceBootMode": "uefi",
                    "NetworkPerformanceOptions": {
                        "BandwidthWeighting": "default"
                    },
                    "Operator": {
                        "Managed": false
                    },
                    "InstanceId": "i-05581a935171c6bd1",
                    "ImageId": "ami-06589f7037b0a7e32",
                    "State": {
                        "Code": 16,
                        "Name": "running"
                    },
                    "PrivateDnsName": "ip-172-30-1-247.ap-northeast-2.compute.internal",
                    "PublicDnsName": "ec2-13-125-203-237.ap-northeast-2.compute.amazonaws.com",
                    "StateTransitionReason": "",
                    "AmiLaunchIndex": 0,
                    "ProductCodes": [],
                    "InstanceType": "m6g.medium",
                    "LaunchTime": "2026-03-06T09:13:31+00:00",
                    "Placement": {
                        "AvailabilityZoneId": "apne2-az2",
                        "GroupName": "",
                        "Tenancy": "default",
                        "AvailabilityZone": "ap-northeast-2b"
                    },
                    "Monitoring": {
                        "State": "disabled"
                    },
                    "SubnetId": "subnet-09231ed7ecf59cfa4",
                    "VpcId": "vpc-0831a2484f9b114c2",
                    "PrivateIpAddress": "172.30.1.247",
                    "PublicIpAddress": "13.125.203.237"
                }
            ]
        },
        {
            "ReservationId": "r-00e5e3b1fc508d70f",
            "OwnerId": "809466760795",
            "RequesterId": "722737459838",
            "Groups": [],
            "Instances": [
                {
                    "Architecture": "arm64",
                    "BlockDeviceMappings": [
                        {
                            "DeviceName": "/dev/xvda",
                            "Ebs": {
                                "AttachTime": "2026-03-06T09:06:28+00:00",
                                "DeleteOnTermination": true,
                                "Status": "attached",
                                "VolumeId": "vol-083ac96dd7602bb82",
                                "EbsCardIndex": 0
                            }
                        }
                    ],
                    "ClientToken": "26b67309-97c6-c6e1-5aa8-04e5ceb9ebae",
                    "EbsOptimized": false,
                    "EnaSupport": true,
                    "Hypervisor": "xen",
                    "IamInstanceProfile": {
                        "Arn": "arn:aws:iam::809466760795:instance-profile/academy-ec2-role",
                        "Id": "AIPA3Y572RZNQDBTRV633"
                    },
                    "NetworkInterfaces": [
                        {
                            "Association": {
                                "IpOwnerId": "amazon",
                                "PublicDnsName": "ec2-54-181-1-24.ap-northeast-2.compute.amazonaws.com",
                                "PublicIp": "54.181.1.24"
                            },
                            "Attachment": {
                                "AttachTime": "2026-03-06T09:06:28+00:00",
                                "AttachmentId": "eni-attach-06346140227edda08",
                                "DeleteOnTermination": true,
                                "DeviceIndex": 0,
                                "Status": "attached",
                                "NetworkCardIndex": 0
                            },
                            "Description": "",
                            "Groups": [
                                {
                                    "GroupId": "sg-088fa3315c12754d0",
                                    "GroupName": "academy-v1-sg-app"
                                }
                            ],
                            "Ipv6Addresses": [],
                            "MacAddress": "06:3b:dd:aa:b5:21",
                            "NetworkInterfaceId": "eni-02364086df16dee7d",
                            "OwnerId": "809466760795",
                            "PrivateDnsName": "ip-172-30-1-31.ap-northeast-2.compute.internal",
                            "PrivateIpAddress": "172.30.1.31",
                            "PrivateIpAddresses": [
                                {
                                    "Association": {
                                        "IpOwnerId": "amazon",
                                        "PublicDnsName": "ec2-54-181-1-24.ap-northeast-2.compute.amazonaws.com",
                                        "PublicIp": "54.181.1.24"
                                    },
                                    "Primary": true,
                                    "PrivateDnsName": "ip-172-30-1-31.ap-northeast-2.compute.internal",
                                    "PrivateIpAddress": "172.30.1.31"
                                }
                            ],
                            "SourceDestCheck": true,
                            "Status": "in-use",
                            "SubnetId": "subnet-09231ed7ecf59cfa4",
                            "VpcId": "vpc-0831a2484f9b114c2",
                            "InterfaceType": "interface",
                            "Operator": {
                                "Managed": false
                            }
                        }
                    ],
                    "RootDeviceName": "/dev/xvda",
                    "RootDeviceType": "ebs",
                    "SecurityGroups": [
                        {
                            "GroupId": "sg-088fa3315c12754d0",
                            "GroupName": "academy-v1-sg-app"
                        }
                    ],
                    "SourceDestCheck": true,
                    "Tags": [
                        {
                            "Key": "Name",
                            "Value": "academy-v1-api"
                        },
                        {
                            "Key": "aws:ec2launchtemplate:id",
                            "Value": "lt-0ba9cc50ab9fe1b10"
                        },
                        {
                            "Key": "aws:ec2launchtemplate:version",
                            "Value": "19"
                        },
                        {
                            "Key": "aws:autoscaling:groupName",
                            "Value": "academy-v1-api-asg"
                        }
                    ],
                    "VirtualizationType": "hvm",
                    "CpuOptions": {
                        "CoreCount": 2,
                        "ThreadsPerCore": 1
                    },
                    "CapacityReservationSpecification": {
                        "CapacityReservationPreference": "open"
                    },
                    "HibernationOptions": {
                        "Configured": false
                    },
                    "MetadataOptions": {
                        "State": "applied",
                        "HttpTokens": "required",
                        "HttpPutResponseHopLimit": 2,
                        "HttpEndpoint": "enabled",
                        "HttpProtocolIpv6": "disabled",
                        "InstanceMetadataTags": "disabled"
                    },
                    "EnclaveOptions": {
                        "Enabled": false
                    },
                    "BootMode": "uefi",
                    "PlatformDetails": "Linux/UNIX",
                    "UsageOperation": "RunInstances",
                    "UsageOperationUpdateTime": "2026-03-06T09:06:28+00:00",
                    "PrivateDnsNameOptions": {
                        "HostnameType": "ip-name",
                        "EnableResourceNameDnsARecord": false,
                        "EnableResourceNameDnsAAAARecord": false
                    },
                    "MaintenanceOptions": {
                        "AutoRecovery": "default",
                        "RebootMigration": "default"
                    },
                    "CurrentInstanceBootMode": "uefi",
                    "NetworkPerformanceOptions": {
                        "BandwidthWeighting": "default"
                    },
                    "Operator": {
                        "Managed": false
                    },
                    "InstanceId": "i-0d3aaca239fd1637e",
                    "ImageId": "ami-0885e191a9bcf28b0",
                    "State": {
                        "Code": 16,
                        "Name": "running"
                    },
                    "PrivateDnsName": "ip-172-30-1-31.ap-northeast-2.compute.internal",
                    "PublicDnsName": "ec2-54-181-1-24.ap-northeast-2.compute.amazonaws.com",
                    "StateTransitionReason": "",
                    "AmiLaunchIndex": 0,
                    "ProductCodes": [],
                    "InstanceType": "t4g.medium",
                    "LaunchTime": "2026-03-06T09:06:28+00:00",
                    "Placement": {
                        "AvailabilityZoneId": "apne2-az2",
                        "GroupName": "",
                        "Tenancy": "default",
                        "AvailabilityZone": "ap-northeast-2b"
                    },
                    "Monitoring": {
                        "State": "disabled"
                    },
                    "SubnetId": "subnet-09231ed7ecf59cfa4",
                    "VpcId": "vpc-0831a2484f9b114c2",
                    "PrivateIpAddress": "172.30.1.31",
                    "PublicIpAddress": "54.181.1.24"
                }
            ]
        },
        {
            "ReservationId": "r-08d5db400246ce79f",
            "OwnerId": "809466760795",
            "RequesterId": "722737459838",
            "Groups": [],
            "Instances": [
                {
                    "Architecture": "arm64",
                    "BlockDeviceMappings": [],
                    "ClientToken": "64f67309-9022-a730-3b99-f21a86bc158e",
                    "EbsOptimized": false,
                    "EnaSupport": true,
                    "Hypervisor": "xen",
                    "NetworkInterfaces": [],
                    "RootDeviceName": "/dev/xvda",
                    "RootDeviceType": "ebs",
                    "SecurityGroups": [],
                    "StateReason": {
                        "Code": "Client.UserInitiatedShutdown",
                        "Message": "Client.UserInitiatedShutdown: User initiated shutdown"
                    },
                    "Tags": [
                        {
                            "Key": "aws:autoscaling:groupName",
                            "Value": "academy-v1-api-asg"
                        },
                        {
                            "Key": "aws:ec2launchtemplate:id",
                            "Value": "lt-0ba9cc50ab9fe1b10"
                        },
                        {
                            "Key": "Name",
                            "Value": "academy-v1-api"
                        },
                        {
                            "Key": "aws:ec2launchtemplate:version",
                            "Value": "18"
                        }
                    ],
                    "VirtualizationType": "hvm",
                    "CpuOptions": {
                        "CoreCount": 2,
                        "ThreadsPerCore": 1
                    },
                    "CapacityReservationSpecification": {
                        "CapacityReservationPreference": "open"
                    },
                    "HibernationOptions": {
                        "Configured": false
                    },
                    "MetadataOptions": {
                        "State": "pending",
                        "HttpTokens": "required",
                        "HttpPutResponseHopLimit": 2,
                        "HttpEndpoint": "enabled",
                        "HttpProtocolIpv6": "disabled",
                        "InstanceMetadataTags": "disabled"
                    },
                    "EnclaveOptions": {
                        "Enabled": false
                    },
                    "BootMode": "uefi",
                    "PlatformDetails": "Linux/UNIX",
                    "UsageOperation": "RunInstances",
                    "UsageOperationUpdateTime": "2026-03-06T09:04:22+00:00",
                    "MaintenanceOptions": {
                        "AutoRecovery": "default",
                        "RebootMigration": "default"
                    },
                    "CurrentInstanceBootMode": "uefi",
                    "NetworkPerformanceOptions": {
                        "BandwidthWeighting": "default"
                    },
                    "Operator": {
                        "Managed": false
                    },
                    "InstanceId": "i-06b1d9b52935fd387",
                    "ImageId": "ami-0885e191a9bcf28b0",
                    "State": {
                        "Code": 48,
                        "Name": "terminated"
                    },
                    "PrivateDnsName": "",
                    "PublicDnsName": "",
                    "StateTransitionReason": "User initiated (2026-03-06 09:11:28 GMT)",
                    "AmiLaunchIndex": 0,
                    "ProductCodes": [],
                    "InstanceType": "t4g.medium",
                    "LaunchTime": "2026-03-06T09:04:22+00:00",
                    "Placement": {
                        "AvailabilityZoneId": "apne2-az2",
                        "GroupName": "",
                        "Tenancy": "default",
                        "AvailabilityZone": "ap-northeast-2b"
                    },
                    "Monitoring": {
                        "State": "disabled"
                    }
                }
            ]
        },
        {
            "ReservationId": "r-0d8cb12248ae4b3eb",
            "OwnerId": "809466760795",
            "RequesterId": "722737459838",
            "Groups": [],
            "Instances": [
                {
                    "Architecture": "arm64",
                    "BlockDeviceMappings": [
                        {
                            "DeviceName": "/dev/xvda",
                            "Ebs": {
                                "AttachTime": "2026-03-06T06:33:55+00:00",
                                "DeleteOnTermination": true,
                                "Status": "attached",
                                "VolumeId": "vol-05337117186ab3e3d",
                                "EbsCardIndex": 0
                            }
                        }
                    ],
                    "ClientToken": "e7567307-6918-dc6e-4bbc-d28103030d97",
                    "EbsOptimized": false,
                    "EnaSupport": true,
                    "Hypervisor": "xen",
                    "NetworkInterfaces": [
                        {
                            "Association": {
                                "IpOwnerId": "amazon",
                                "PublicDnsName": "ec2-3-36-95-243.ap-northeast-2.compute.amazonaws.com",
                                "PublicIp": "3.36.95.243"
                            },
                            "Attachment": {
                                "AttachTime": "2026-03-06T06:33:54+00:00",
                                "AttachmentId": "eni-attach-06ac7f743ba7fafeb",
                                "DeleteOnTermination": true,
                                "DeviceIndex": 0,
                                "Status": "attached",
                                "NetworkCardIndex": 0
                            },
                            "Description": "",
                            "Groups": [
                                {
                                    "GroupId": "sg-088fa3315c12754d0",
                                    "GroupName": "academy-v1-sg-app"
                                }
                            ],
                            "Ipv6Addresses": [],
                            "MacAddress": "02:47:42:1e:2d:83",
                            "NetworkInterfaceId": "eni-025d66a8e0abb1763",
                            "OwnerId": "809466760795",
                            "PrivateDnsName": "ip-172-30-0-125.ap-northeast-2.compute.internal",
                            "PrivateIpAddress": "172.30.0.125",
                            "PrivateIpAddresses": [
                                {
                                    "Association": {
                                        "IpOwnerId": "amazon",
                                        "PublicDnsName": "ec2-3-36-95-243.ap-northeast-2.compute.amazonaws.com",
                                        "PublicIp": "3.36.95.243"
                                    },
                                    "Primary": true,
                                    "PrivateDnsName": "ip-172-30-0-125.ap-northeast-2.compute.internal",
                                    "PrivateIpAddress": "172.30.0.125"
                                }
                            ],
                            "SourceDestCheck": true,
                            "Status": "in-use",
                            "SubnetId": "subnet-07a8427d3306ce910",
                            "VpcId": "vpc-0831a2484f9b114c2",
                            "InterfaceType": "interface",
                            "Operator": {
                                "Managed": false
                            }
                        }
                    ],
                    "RootDeviceName": "/dev/xvda",
                    "RootDeviceType": "ebs",
                    "SecurityGroups": [
                        {
                            "GroupId": "sg-088fa3315c12754d0",
                            "GroupName": "academy-v1-sg-app"
                        }
                    ],
                    "SourceDestCheck": true,
                    "Tags": [
                        {
                            "Key": "aws:ec2launchtemplate:id",
                            "Value": "lt-07205484847c0d061"
                        },
                        {
                            "Key": "aws:ec2launchtemplate:version",
                            "Value": "2"
                        },
                        {
                            "Key": "Name",
                            "Value": "academy-v1-ai-worker"
                        },
                        {
                            "Key": "aws:autoscaling:groupName",
                            "Value": "academy-v1-ai-worker-asg"
                        }
                    ],
                    "VirtualizationType": "hvm",
                    "CpuOptions": {
                        "CoreCount": 2,
                        "ThreadsPerCore": 1
                    },
                    "CapacityReservationSpecification": {
                        "CapacityReservationPreference": "open"
                    },
                    "HibernationOptions": {
                        "Configured": false
                    },
                    "MetadataOptions": {
                        "State": "applied",
                        "HttpTokens": "required",
                        "HttpPutResponseHopLimit": 2,
                        "HttpEndpoint": "enabled",
                        "HttpProtocolIpv6": "disabled",
                        "InstanceMetadataTags": "disabled"
                    },
                    "EnclaveOptions": {
                        "Enabled": false
                    },
                    "BootMode": "uefi",
                    "PlatformDetails": "Linux/UNIX",
                    "UsageOperation": "RunInstances",
                    "UsageOperationUpdateTime": "2026-03-06T06:33:54+00:00",
                    "PrivateDnsNameOptions": {
                        "HostnameType": "ip-name",
                        "EnableResourceNameDnsARecord": false,
                        "EnableResourceNameDnsAAAARecord": false
                    },
                    "MaintenanceOptions": {
                        "AutoRecovery": "default",
                        "RebootMigration": "default"
                    },
                    "CurrentInstanceBootMode": "uefi",
                    "NetworkPerformanceOptions": {
                        "BandwidthWeighting": "default"
                    },
                    "Operator": {
                        "Managed": false
                    },
                    "InstanceId": "i-0851018cae061ea8d",
                    "ImageId": "ami-0885e191a9bcf28b0",
                    "State": {
                        "Code": 16,
                        "Name": "running"
                    },
                    "PrivateDnsName": "ip-172-30-0-125.ap-northeast-2.compute.internal",
                    "PublicDnsName": "ec2-3-36-95-243.ap-northeast-2.compute.amazonaws.com",
                    "StateTransitionReason": "",
                    "AmiLaunchIndex": 0,
                    "ProductCodes": [],
                    "InstanceType": "t4g.medium",
                    "LaunchTime": "2026-03-06T06:33:54+00:00",
                    "Placement": {
                        "AvailabilityZoneId": "apne2-az1",
                        "GroupName": "",
                        "Tenancy": "default",
                        "AvailabilityZone": "ap-northeast-2a"
                    },
                    "Monitoring": {
                        "State": "disabled"
                    },
                    "SubnetId": "subnet-07a8427d3306ce910",
                    "VpcId": "vpc-0831a2484f9b114c2",
                    "PrivateIpAddress": "172.30.0.125",
                    "PublicIpAddress": "3.36.95.243"
                }
            ]
        },
        {
            "ReservationId": "r-0caaa3bcf9fdbb1d2",
            "OwnerId": "809466760795",
            "RequesterId": "722737459838",
            "Groups": [],
            "Instances": [
                {
                    "Architecture": "arm64",
                    "BlockDeviceMappings": [
                        {
                            "DeviceName": "/dev/xvda",
                            "Ebs": {
                                "AttachTime": "2026-03-06T06:33:54+00:00",
                                "DeleteOnTermination": true,
                                "Status": "attached",
                                "VolumeId": "vol-069bb53dd3144bdb0",
                                "EbsCardIndex": 0
                            }
                        }
                    ],
                    "ClientToken": "85067307-6905-e014-9861-539e6ff9c1f0",
                    "EbsOptimized": false,
                    "EnaSupport": true,
                    "Hypervisor": "xen",
                    "NetworkInterfaces": [
                        {
                            "Association": {
                                "IpOwnerId": "amazon",
                                "PublicDnsName": "ec2-3-35-136-68.ap-northeast-2.compute.amazonaws.com",
                                "PublicIp": "3.35.136.68"
                            },
                            "Attachment": {
                                "AttachTime": "2026-03-06T06:33:53+00:00",
                                "AttachmentId": "eni-attach-0d38f860d2cac1138",
                                "DeleteOnTermination": true,
                                "DeviceIndex": 0,
                                "Status": "attached",
                                "NetworkCardIndex": 0
                            },
                            "Description": "",
                            "Groups": [
                                {
                                    "GroupId": "sg-088fa3315c12754d0",
                                    "GroupName": "academy-v1-sg-app"
                                }
                            ],
                            "Ipv6Addresses": [],
                            "MacAddress": "02:d9:18:8e:16:f7",
                            "NetworkInterfaceId": "eni-00630f4206837a84d",
                            "OwnerId": "809466760795",
                            "PrivateDnsName": "ip-172-30-0-144.ap-northeast-2.compute.internal",
                            "PrivateIpAddress": "172.30.0.144",
                            "PrivateIpAddresses": [
                                {
                                    "Association": {
                                        "IpOwnerId": "amazon",
                                        "PublicDnsName": "ec2-3-35-136-68.ap-northeast-2.compute.amazonaws.com",
                                        "PublicIp": "3.35.136.68"
                                    },
                                    "Primary": true,
                                    "PrivateDnsName": "ip-172-30-0-144.ap-northeast-2.compute.internal",
                                    "PrivateIpAddress": "172.30.0.144"
                                }
                            ],
                            "SourceDestCheck": true,
                            "Status": "in-use",
                            "SubnetId": "subnet-07a8427d3306ce910",
                            "VpcId": "vpc-0831a2484f9b114c2",
                            "InterfaceType": "interface",
                            "Operator": {
                                "Managed": false
                            }
                        }
                    ],
                    "RootDeviceName": "/dev/xvda",
                    "RootDeviceType": "ebs",
                    "SecurityGroups": [
                        {
                            "GroupId": "sg-088fa3315c12754d0",
                            "GroupName": "academy-v1-sg-app"
                        }
                    ],
                    "SourceDestCheck": true,
                    "Tags": [
                        {
                            "Key": "aws:ec2launchtemplate:version",
                            "Value": "3"
                        },
                        {
                            "Key": "Name",
                            "Value": "academy-v1-messaging-worker"
                        },
                        {
                            "Key": "aws:autoscaling:groupName",
                            "Value": "academy-v1-messaging-worker-asg"
                        },
                        {
                            "Key": "aws:ec2launchtemplate:id",
                            "Value": "lt-0dab70932706e8b9c"
                        }
                    ],
                    "VirtualizationType": "hvm",
                    "CpuOptions": {
                        "CoreCount": 2,
                        "ThreadsPerCore": 1
                    },
                    "CapacityReservationSpecification": {
                        "CapacityReservationPreference": "open"
                    },
                    "HibernationOptions": {
                        "Configured": false
                    },
                    "MetadataOptions": {
                        "State": "applied",
                        "HttpTokens": "required",
                        "HttpPutResponseHopLimit": 2,
                        "HttpEndpoint": "enabled",
                        "HttpProtocolIpv6": "disabled",
                        "InstanceMetadataTags": "disabled"
                    },
                    "EnclaveOptions": {
                        "Enabled": false
                    },
                    "BootMode": "uefi",
                    "PlatformDetails": "Linux/UNIX",
                    "UsageOperation": "RunInstances",
                    "UsageOperationUpdateTime": "2026-03-06T06:33:53+00:00",
                    "PrivateDnsNameOptions": {
                        "HostnameType": "ip-name",
                        "EnableResourceNameDnsARecord": false,
                        "EnableResourceNameDnsAAAARecord": false
                    },
                    "MaintenanceOptions": {
                        "AutoRecovery": "default",
                        "RebootMigration": "default"
                    },
                    "CurrentInstanceBootMode": "uefi",
                    "NetworkPerformanceOptions": {
                        "BandwidthWeighting": "default"
                    },
                    "Operator": {
                        "Managed": false
                    },
                    "InstanceId": "i-0b47a6fce4975ec91",
                    "ImageId": "ami-0885e191a9bcf28b0",
                    "State": {
                        "Code": 16,
                        "Name": "running"
                    },
                    "PrivateDnsName": "ip-172-30-0-144.ap-northeast-2.compute.internal",
                    "PublicDnsName": "ec2-3-35-136-68.ap-northeast-2.compute.amazonaws.com",
                    "StateTransitionReason": "",
                    "AmiLaunchIndex": 0,
                    "ProductCodes": [],
                    "InstanceType": "t4g.medium",
                    "LaunchTime": "2026-03-06T06:33:53+00:00",
                    "Placement": {
                        "AvailabilityZoneId": "apne2-az1",
                        "GroupName": "",
                        "Tenancy": "default",
                        "AvailabilityZone": "ap-northeast-2a"
                    },
                    "Monitoring": {
                        "State": "disabled"
                    },
                    "SubnetId": "subnet-07a8427d3306ce910",
                    "VpcId": "vpc-0831a2484f9b114c2",
                    "PrivateIpAddress": "172.30.0.144",
                    "PublicIpAddress": "3.35.136.68"
                }
            ]
        },
        {
            "ReservationId": "r-06fbec5e0693eafc0",
            "OwnerId": "809466760795",
            "RequesterId": "722737459838",
            "Groups": [],
            "Instances": [
                {
                    "Architecture": "arm64",
                    "BlockDeviceMappings": [],
                    "ClientToken": "f7467308-c573-0da0-1955-db3962966004",
                    "EbsOptimized": false,
                    "EnaSupport": true,
                    "Hypervisor": "xen",
                    "NetworkInterfaces": [],
                    "RootDeviceName": "/dev/xvda",
                    "RootDeviceType": "ebs",
                    "SecurityGroups": [],
                    "StateReason": {
                        "Code": "Client.UserInitiatedShutdown",
                        "Message": "Client.UserInitiatedShutdown: User initiated shutdown"
                    },
                    "Tags": [
                        {
                            "Key": "aws:autoscaling:groupName",
                            "Value": "academy-v1-api-asg"
                        },
                        {
                            "Key": "Name",
                            "Value": "academy-v1-api"
                        },
                        {
                            "Key": "aws:ec2launchtemplate:id",
                            "Value": "lt-0ba9cc50ab9fe1b10"
                        },
                        {
                            "Key": "aws:ec2launchtemplate:version",
                            "Value": "16"
                        }
                    ],
                    "VirtualizationType": "hvm",
                    "CpuOptions": {
                        "CoreCount": 2,
                        "ThreadsPerCore": 1
                    },
                    "CapacityReservationSpecification": {
                        "CapacityReservationPreference": "open"
                    },
                    "HibernationOptions": {
                        "Configured": false
                    },
                    "MetadataOptions": {
                        "State": "pending",
                        "HttpTokens": "required",
                        "HttpPutResponseHopLimit": 2,
                        "HttpEndpoint": "enabled",
                        "HttpProtocolIpv6": "disabled",
                        "InstanceMetadataTags": "disabled"
                    },
                    "EnclaveOptions": {
                        "Enabled": false
                    },
                    "BootMode": "uefi",
                    "PlatformDetails": "Linux/UNIX",
                    "UsageOperation": "RunInstances",
                    "UsageOperationUpdateTime": "2026-03-06T08:09:02+00:00",
                    "MaintenanceOptions": {
                        "AutoRecovery": "default",
                        "RebootMigration": "default"
                    },
                    "CurrentInstanceBootMode": "uefi",
                    "NetworkPerformanceOptions": {
                        "BandwidthWeighting": "default"
                    },
                    "Operator": {
                        "Managed": false
                    },
                    "InstanceId": "i-0fbb224e2ed66f115",
                    "ImageId": "ami-0885e191a9bcf28b0",
                    "State": {
                        "Code": 48,
                        "Name": "terminated"
                    },
                    "PrivateDnsName": "",
                    "PublicDnsName": "",
                    "StateTransitionReason": "User initiated (2026-03-06 08:26:37 GMT)",
                    "AmiLaunchIndex": 0,
                    "ProductCodes": [],
                    "InstanceType": "t4g.medium",
                    "LaunchTime": "2026-03-06T08:09:02+00:00",
                    "Placement": {
                        "AvailabilityZoneId": "apne2-az1",
                        "GroupName": "",
                        "Tenancy": "default",
                        "AvailabilityZone": "ap-northeast-2a"
                    },
                    "Monitoring": {
                        "State": "disabled"
                    }
                }
            ]
        },
        {
            "ReservationId": "r-03372f54603e7f880",
            "OwnerId": "809466760795",
            "RequesterId": "722737459838",
            "Groups": [],
            "Instances": [
                {
                    "Architecture": "arm64",
                    "BlockDeviceMappings": [],
                    "ClientToken": "8f967308-f38f-7542-1e4f-e766fd1c2746",
                    "EbsOptimized": false,
                    "EnaSupport": true,
                    "Hypervisor": "xen",
                    "NetworkInterfaces": [],
                    "RootDeviceName": "/dev/xvda",
                    "RootDeviceType": "ebs",
                    "SecurityGroups": [],
                    "StateReason": {
                        "Code": "Client.UserInitiatedShutdown",
                        "Message": "Client.UserInitiatedShutdown: User initiated shutdown"
                    },
                    "Tags": [
                        {
                            "Key": "aws:autoscaling:groupName",
                            "Value": "academy-v1-api-asg"
                        },
                        {
                            "Key": "Name",
                            "Value": "academy-v1-api"
                        },
                        {
                            "Key": "aws:ec2launchtemplate:id",
                            "Value": "lt-0ba9cc50ab9fe1b10"
                        },
                        {
                            "Key": "aws:ec2launchtemplate:version",
                            "Value": "16"
                        }
                    ],
                    "VirtualizationType": "hvm",
                    "CpuOptions": {
                        "CoreCount": 2,
                        "ThreadsPerCore": 1
                    },
                    "CapacityReservationSpecification": {
                        "CapacityReservationPreference": "open"
                    },
                    "HibernationOptions": {
                        "Configured": false
                    },
                    "MetadataOptions": {
                        "State": "pending",
                        "HttpTokens": "required",
                        "HttpPutResponseHopLimit": 2,
                        "HttpEndpoint": "enabled",
                        "HttpProtocolIpv6": "disabled",
                        "InstanceMetadataTags": "disabled"
                    },
                    "EnclaveOptions": {
                        "Enabled": false
                    },
                    "BootMode": "uefi",
                    "PlatformDetails": "Linux/UNIX",
                    "UsageOperation": "RunInstances",
                    "UsageOperationUpdateTime": "2026-03-06T08:21:37+00:00",
                    "MaintenanceOptions": {
                        "AutoRecovery": "default",
                        "RebootMigration": "default"
                    },
                    "CurrentInstanceBootMode": "uefi",
                    "NetworkPerformanceOptions": {
                        "BandwidthWeighting": "default"
                    },
                    "Operator": {
                        "Managed": false
                    },
                    "InstanceId": "i-019c2c99b692c8fbc",
                    "ImageId": "ami-0885e191a9bcf28b0",
                    "State": {
                        "Code": 48,
                        "Name": "terminated"
                    },
                    "PrivateDnsName": "",
                    "PublicDnsName": "",
                    "StateTransitionReason": "User initiated (2026-03-06 08:53:29 GMT)",
                    "AmiLaunchIndex": 0,
                    "ProductCodes": [],
                    "InstanceType": "t4g.medium",
                    "LaunchTime": "2026-03-06T08:21:37+00:00",
                    "Placement": {
                        "AvailabilityZoneId": "apne2-az1",
                        "GroupName": "",
                        "Tenancy": "default",
                        "AvailabilityZone": "ap-northeast-2a"
                    },
                    "Monitoring": {
                        "State": "disabled"
                    }
                }
            ]
        },
        {
            "ReservationId": "r-0fdcaac656701efc2",
            "OwnerId": "809466760795",
            "RequesterId": "722737459838",
            "Groups": [],
            "Instances": [
                {
                    "Architecture": "arm64",
                    "BlockDeviceMappings": [],
                    "ClientToken": "9e467309-55ea-c97f-1918-4b6628ca36ad",
                    "EbsOptimized": false,
                    "EnaSupport": true,
                    "Hypervisor": "xen",
                    "NetworkInterfaces": [],
                    "RootDeviceName": "/dev/xvda",
                    "RootDeviceType": "ebs",
                    "SecurityGroups": [],
                    "StateReason": {
                        "Code": "Client.UserInitiatedShutdown",
                        "Message": "Client.UserInitiatedShutdown: User initiated shutdown"
                    },
                    "Tags": [
                        {
                            "Key": "aws:ec2launchtemplate:version",
                            "Value": "17"
                        },
                        {
                            "Key": "aws:autoscaling:groupName",
                            "Value": "academy-v1-api-asg"
                        },
                        {
                            "Key": "Name",
                            "Value": "academy-v1-api"
                        },
                        {
                            "Key": "aws:ec2launchtemplate:id",
                            "Value": "lt-0ba9cc50ab9fe1b10"
                        }
                    ],
                    "VirtualizationType": "hvm",
                    "CpuOptions": {
                        "CoreCount": 2,
                        "ThreadsPerCore": 1
                    },
                    "CapacityReservationSpecification": {
                        "CapacityReservationPreference": "open"
                    },
                    "HibernationOptions": {
                        "Configured": false
                    },
                    "MetadataOptions": {
                        "State": "pending",
                        "HttpTokens": "required",
                        "HttpPutResponseHopLimit": 2,
                        "HttpEndpoint": "enabled",
                        "HttpProtocolIpv6": "disabled",
                        "InstanceMetadataTags": "disabled"
                    },
                    "EnclaveOptions": {
                        "Enabled": false
                    },
                    "BootMode": "uefi",
                    "PlatformDetails": "Linux/UNIX",
                    "UsageOperation": "RunInstances",
                    "UsageOperationUpdateTime": "2026-03-06T08:48:29+00:00",
                    "MaintenanceOptions": {
                        "AutoRecovery": "default",
                        "RebootMigration": "default"
                    },
                    "CurrentInstanceBootMode": "uefi",
                    "NetworkPerformanceOptions": {
                        "BandwidthWeighting": "default"
                    },
                    "Operator": {
                        "Managed": false
                    },
                    "InstanceId": "i-0fe5beb0b6914ea56",
                    "ImageId": "ami-0885e191a9bcf28b0",
                    "State": {
                        "Code": 48,
                        "Name": "terminated"
                    },
                    "PrivateDnsName": "",
                    "PublicDnsName": "",
                    "StateTransitionReason": "User initiated (2026-03-06 09:00:17 GMT)",
                    "AmiLaunchIndex": 0,
                    "ProductCodes": [],
                    "InstanceType": "t4g.medium",
                    "LaunchTime": "2026-03-06T08:48:29+00:00",
                    "Placement": {
                        "AvailabilityZoneId": "apne2-az1",
                        "GroupName": "",
                        "Tenancy": "default",
                        "AvailabilityZone": "ap-northeast-2a"
                    },
                    "Monitoring": {
                        "State": "disabled"
                    }
                }
            ]
        }
    ]
}
